{
	"id": 0,
	"name": "@galacean/engine-physics-physx",
	"kind": 1,
	"kindString": "Project",
	"flags": {},
	"originalName": "",
	"children": [
		{
			"id": 93,
			"name": "PhysXRuntimeMode",
			"kind": 8,
			"kindString": "Enumeration",
			"flags": {},
			"comment": {
				"summary": [
					{
						"kind": "text",
						"text": "PhysX runtime mode."
					}
				]
			},
			"children": [
				{
					"id": 94,
					"name": "Auto",
					"kind": 16,
					"kindString": "Enumeration Member",
					"flags": {},
					"comment": {
						"summary": [
							{
								"kind": "text",
								"text": "Use webAssembly mode first, if WebAssembly mode is not supported, roll back to JavaScript mode."
							}
						]
					},
					"sources": [
						{
							"fileName": "enum/PhysXRuntimeMode.ts",
							"line": 6,
							"character": 2,
							"url": "https://github.com/galacean/engine/blob/bfd0960a/packages/physics-physx/src/enum/PhysXRuntimeMode.ts#L6"
						}
					],
					"type": {
						"type": "literal",
						"value": 0
					}
				},
				{
					"id": 96,
					"name": "JavaScript",
					"kind": 16,
					"kindString": "Enumeration Member",
					"flags": {},
					"comment": {
						"summary": [
							{
								"kind": "text",
								"text": "JavaScript mode."
							}
						]
					},
					"sources": [
						{
							"fileName": "enum/PhysXRuntimeMode.ts",
							"line": 10,
							"character": 2,
							"url": "https://github.com/galacean/engine/blob/bfd0960a/packages/physics-physx/src/enum/PhysXRuntimeMode.ts#L10"
						}
					],
					"type": {
						"type": "literal",
						"value": 2
					}
				},
				{
					"id": 95,
					"name": "WebAssembly",
					"kind": 16,
					"kindString": "Enumeration Member",
					"flags": {},
					"comment": {
						"summary": [
							{
								"kind": "text",
								"text": "WebAssembly mode."
							}
						]
					},
					"sources": [
						{
							"fileName": "enum/PhysXRuntimeMode.ts",
							"line": 8,
							"character": 2,
							"url": "https://github.com/galacean/engine/blob/bfd0960a/packages/physics-physx/src/enum/PhysXRuntimeMode.ts#L8"
						}
					],
					"type": {
						"type": "literal",
						"value": 1
					}
				}
			],
			"groups": [
				{
					"title": "Enumeration Members",
					"children": [
						94,
						96,
						95
					]
				}
			],
			"sources": [
				{
					"fileName": "enum/PhysXRuntimeMode.ts",
					"line": 4,
					"character": 12,
					"url": "https://github.com/galacean/engine/blob/bfd0960a/packages/physics-physx/src/enum/PhysXRuntimeMode.ts#L4"
				}
			]
		},
		{
			"id": 1,
			"name": "PhysXPhysics",
			"kind": 128,
			"kindString": "Class",
			"flags": {},
			"comment": {
				"summary": [
					{
						"kind": "text",
						"text": "PhysX object creation."
					}
				]
			},
			"children": [
				{
					"id": 91,
					"name": "constructor",
					"kind": 512,
					"kindString": "Constructor",
					"flags": {},
					"signatures": [
						{
							"id": 92,
							"name": "new PhysXPhysics",
							"kind": 16384,
							"kindString": "Constructor signature",
							"flags": {},
							"type": {
								"type": "reference",
								"id": 1,
								"name": "PhysXPhysics"
							}
						}
					]
				},
				{
					"id": 88,
					"name": "_init",
					"kind": 2048,
					"kindString": "Method",
					"flags": {
						"isPrivate": true,
						"isStatic": true
					},
					"sources": [
						{
							"fileName": "PhysXPhysics.ts",
							"line": 223,
							"character": 17,
							"url": "https://github.com/galacean/engine/blob/bfd0960a/packages/physics-physx/src/PhysXPhysics.ts#L223"
						}
					],
					"signatures": [
						{
							"id": 89,
							"name": "_init",
							"kind": 4096,
							"kindString": "Call signature",
							"flags": {},
							"parameters": [
								{
									"id": 90,
									"name": "physX",
									"kind": 32768,
									"kindString": "Parameter",
									"flags": {},
									"type": {
										"type": "intrinsic",
										"name": "any"
									}
								}
							],
							"type": {
								"type": "intrinsic",
								"name": "void"
							}
						}
					]
				},
				{
					"id": 59,
					"name": "createBoxColliderShape",
					"kind": 2048,
					"kindString": "Method",
					"flags": {
						"isStatic": true
					},
					"sources": [
						{
							"fileName": "PhysXPhysics.ts",
							"line": 168,
							"character": 9,
							"url": "https://github.com/galacean/engine/blob/bfd0960a/packages/physics-physx/src/PhysXPhysics.ts#L168"
						}
					],
					"signatures": [
						{
							"id": 60,
							"name": "createBoxColliderShape",
							"kind": 4096,
							"kindString": "Call signature",
							"flags": {},
							"comment": {
								"summary": [
									{
										"kind": "inline-tag",
										"tag": "@inheritDoc",
										"text": "IPhysics.createBoxColliderShape"
									}
								]
							},
							"parameters": [
								{
									"id": 61,
									"name": "uniqueID",
									"kind": 32768,
									"kindString": "Parameter",
									"flags": {},
									"type": {
										"type": "intrinsic",
										"name": "number"
									}
								},
								{
									"id": 62,
									"name": "size",
									"kind": 32768,
									"kindString": "Parameter",
									"flags": {},
									"type": {
										"type": "reference",
										"name": "Vector3"
									}
								},
								{
									"id": 63,
									"name": "material",
									"kind": 32768,
									"kindString": "Parameter",
									"flags": {},
									"type": {
										"type": "reference",
										"name": "PhysXPhysicsMaterial"
									}
								}
							],
							"type": {
								"type": "reference",
								"name": "IBoxColliderShape"
							}
						}
					]
				},
				{
					"id": 73,
					"name": "createCapsuleColliderShape",
					"kind": 2048,
					"kindString": "Method",
					"flags": {
						"isStatic": true
					},
					"sources": [
						{
							"fileName": "PhysXPhysics.ts",
							"line": 193,
							"character": 9,
							"url": "https://github.com/galacean/engine/blob/bfd0960a/packages/physics-physx/src/PhysXPhysics.ts#L193"
						}
					],
					"signatures": [
						{
							"id": 74,
							"name": "createCapsuleColliderShape",
							"kind": 4096,
							"kindString": "Call signature",
							"flags": {},
							"comment": {
								"summary": [
									{
										"kind": "inline-tag",
										"tag": "@inheritDoc",
										"text": "IPhysics.createCapsuleColliderShape"
									}
								]
							},
							"parameters": [
								{
									"id": 75,
									"name": "uniqueID",
									"kind": 32768,
									"kindString": "Parameter",
									"flags": {},
									"type": {
										"type": "intrinsic",
										"name": "number"
									}
								},
								{
									"id": 76,
									"name": "radius",
									"kind": 32768,
									"kindString": "Parameter",
									"flags": {},
									"type": {
										"type": "intrinsic",
										"name": "number"
									}
								},
								{
									"id": 77,
									"name": "height",
									"kind": 32768,
									"kindString": "Parameter",
									"flags": {},
									"type": {
										"type": "intrinsic",
										"name": "number"
									}
								},
								{
									"id": 78,
									"name": "material",
									"kind": 32768,
									"kindString": "Parameter",
									"flags": {},
									"type": {
										"type": "reference",
										"name": "PhysXPhysicsMaterial"
									}
								}
							],
							"type": {
								"type": "reference",
								"name": "ICapsuleColliderShape"
							}
						}
					]
				},
				{
					"id": 50,
					"name": "createCharacterController",
					"kind": 2048,
					"kindString": "Method",
					"flags": {
						"isStatic": true
					},
					"sources": [
						{
							"fileName": "PhysXPhysics.ts",
							"line": 148,
							"character": 9,
							"url": "https://github.com/galacean/engine/blob/bfd0960a/packages/physics-physx/src/PhysXPhysics.ts#L148"
						}
					],
					"signatures": [
						{
							"id": 51,
							"name": "createCharacterController",
							"kind": 4096,
							"kindString": "Call signature",
							"flags": {},
							"comment": {
								"summary": [
									{
										"kind": "inline-tag",
										"tag": "@inheritDoc",
										"text": "IPhysics.createCharacterController"
									}
								]
							},
							"type": {
								"type": "reference",
								"name": "ICharacterController"
							}
						}
					]
				},
				{
					"id": 46,
					"name": "createDynamicCollider",
					"kind": 2048,
					"kindString": "Method",
					"flags": {
						"isStatic": true
					},
					"sources": [
						{
							"fileName": "PhysXPhysics.ts",
							"line": 141,
							"character": 9,
							"url": "https://github.com/galacean/engine/blob/bfd0960a/packages/physics-physx/src/PhysXPhysics.ts#L141"
						}
					],
					"signatures": [
						{
							"id": 47,
							"name": "createDynamicCollider",
							"kind": 4096,
							"kindString": "Call signature",
							"flags": {},
							"comment": {
								"summary": [
									{
										"kind": "inline-tag",
										"tag": "@inheritDoc",
										"text": "IPhysics.createDynamicCollider"
									}
								]
							},
							"parameters": [
								{
									"id": 48,
									"name": "position",
									"kind": 32768,
									"kindString": "Parameter",
									"flags": {},
									"type": {
										"type": "reference",
										"name": "Vector3"
									}
								},
								{
									"id": 49,
									"name": "rotation",
									"kind": 32768,
									"kindString": "Parameter",
									"flags": {},
									"type": {
										"type": "reference",
										"name": "Quaternion"
									}
								}
							],
							"type": {
								"type": "reference",
								"name": "IDynamicCollider"
							}
						}
					]
				},
				{
					"id": 79,
					"name": "createFixedJoint",
					"kind": 2048,
					"kindString": "Method",
					"flags": {
						"isStatic": true
					},
					"sources": [
						{
							"fileName": "PhysXPhysics.ts",
							"line": 205,
							"character": 9,
							"url": "https://github.com/galacean/engine/blob/bfd0960a/packages/physics-physx/src/PhysXPhysics.ts#L205"
						}
					],
					"signatures": [
						{
							"id": 80,
							"name": "createFixedJoint",
							"kind": 4096,
							"kindString": "Call signature",
							"flags": {},
							"comment": {
								"summary": [
									{
										"kind": "inline-tag",
										"tag": "@inheritDoc",
										"text": "IPhysics.createFixedJoint"
									}
								]
							},
							"parameters": [
								{
									"id": 81,
									"name": "collider",
									"kind": 32768,
									"kindString": "Parameter",
									"flags": {},
									"type": {
										"type": "reference",
										"name": "PhysXCollider"
									}
								}
							],
							"type": {
								"type": "reference",
								"name": "IFixedJoint"
							}
						}
					]
				},
				{
					"id": 82,
					"name": "createHingeJoint",
					"kind": 2048,
					"kindString": "Method",
					"flags": {
						"isStatic": true
					},
					"sources": [
						{
							"fileName": "PhysXPhysics.ts",
							"line": 212,
							"character": 9,
							"url": "https://github.com/galacean/engine/blob/bfd0960a/packages/physics-physx/src/PhysXPhysics.ts#L212"
						}
					],
					"signatures": [
						{
							"id": 83,
							"name": "createHingeJoint",
							"kind": 4096,
							"kindString": "Call signature",
							"flags": {},
							"comment": {
								"summary": [
									{
										"kind": "inline-tag",
										"tag": "@inheritDoc",
										"text": "IPhysics.createHingeJoint"
									}
								]
							},
							"parameters": [
								{
									"id": 84,
									"name": "collider",
									"kind": 32768,
									"kindString": "Parameter",
									"flags": {},
									"type": {
										"type": "reference",
										"name": "PhysXCollider"
									}
								}
							],
							"type": {
								"type": "reference",
								"name": "IHingeJoint"
							}
						}
					]
				},
				{
					"id": 10,
					"name": "createPhysicsManager",
					"kind": 2048,
					"kindString": "Method",
					"flags": {
						"isStatic": true
					},
					"sources": [
						{
							"fileName": "PhysXPhysics.ts",
							"line": 113,
							"character": 9,
							"url": "https://github.com/galacean/engine/blob/bfd0960a/packages/physics-physx/src/PhysXPhysics.ts#L113"
						}
					],
					"signatures": [
						{
							"id": 11,
							"name": "createPhysicsManager",
							"kind": 4096,
							"kindString": "Call signature",
							"flags": {},
							"comment": {
								"summary": [
									{
										"kind": "inline-tag",
										"tag": "@inheritDoc",
										"text": "IPhysics.createPhysicsManager"
									}
								]
							},
							"parameters": [
								{
									"id": 12,
									"name": "onContactBegin",
									"kind": 32768,
									"kindString": "Parameter",
									"flags": {
										"isOptional": true
									},
									"type": {
										"type": "reflection",
										"declaration": {
											"id": 13,
											"name": "__type",
											"kind": 65536,
											"kindString": "Type literal",
											"flags": {},
											"sources": [
												{
													"fileName": "PhysXPhysics.ts",
													"line": 114,
													"character": 21,
													"url": "https://github.com/galacean/engine/blob/bfd0960a/packages/physics-physx/src/PhysXPhysics.ts#L114"
												}
											],
											"signatures": [
												{
													"id": 14,
													"name": "__type",
													"kind": 4096,
													"kindString": "Call signature",
													"flags": {},
													"parameters": [
														{
															"id": 15,
															"name": "obj1",
															"kind": 32768,
															"kindString": "Parameter",
															"flags": {},
															"type": {
																"type": "intrinsic",
																"name": "number"
															}
														},
														{
															"id": 16,
															"name": "obj2",
															"kind": 32768,
															"kindString": "Parameter",
															"flags": {},
															"type": {
																"type": "intrinsic",
																"name": "number"
															}
														}
													],
													"type": {
														"type": "intrinsic",
														"name": "void"
													}
												}
											]
										}
									}
								},
								{
									"id": 17,
									"name": "onContactEnd",
									"kind": 32768,
									"kindString": "Parameter",
									"flags": {
										"isOptional": true
									},
									"type": {
										"type": "reflection",
										"declaration": {
											"id": 18,
											"name": "__type",
											"kind": 65536,
											"kindString": "Type literal",
											"flags": {},
											"sources": [
												{
													"fileName": "PhysXPhysics.ts",
													"line": 115,
													"character": 19,
													"url": "https://github.com/galacean/engine/blob/bfd0960a/packages/physics-physx/src/PhysXPhysics.ts#L115"
												}
											],
											"signatures": [
												{
													"id": 19,
													"name": "__type",
													"kind": 4096,
													"kindString": "Call signature",
													"flags": {},
													"parameters": [
														{
															"id": 20,
															"name": "obj1",
															"kind": 32768,
															"kindString": "Parameter",
															"flags": {},
															"type": {
																"type": "intrinsic",
																"name": "number"
															}
														},
														{
															"id": 21,
															"name": "obj2",
															"kind": 32768,
															"kindString": "Parameter",
															"flags": {},
															"type": {
																"type": "intrinsic",
																"name": "number"
															}
														}
													],
													"type": {
														"type": "intrinsic",
														"name": "void"
													}
												}
											]
										}
									}
								},
								{
									"id": 22,
									"name": "onContactStay",
									"kind": 32768,
									"kindString": "Parameter",
									"flags": {
										"isOptional": true
									},
									"type": {
										"type": "reflection",
										"declaration": {
											"id": 23,
											"name": "__type",
											"kind": 65536,
											"kindString": "Type literal",
											"flags": {},
											"sources": [
												{
													"fileName": "PhysXPhysics.ts",
													"line": 116,
													"character": 20,
													"url": "https://github.com/galacean/engine/blob/bfd0960a/packages/physics-physx/src/PhysXPhysics.ts#L116"
												}
											],
											"signatures": [
												{
													"id": 24,
													"name": "__type",
													"kind": 4096,
													"kindString": "Call signature",
													"flags": {},
													"parameters": [
														{
															"id": 25,
															"name": "obj1",
															"kind": 32768,
															"kindString": "Parameter",
															"flags": {},
															"type": {
																"type": "intrinsic",
																"name": "number"
															}
														},
														{
															"id": 26,
															"name": "obj2",
															"kind": 32768,
															"kindString": "Parameter",
															"flags": {},
															"type": {
																"type": "intrinsic",
																"name": "number"
															}
														}
													],
													"type": {
														"type": "intrinsic",
														"name": "void"
													}
												}
											]
										}
									}
								},
								{
									"id": 27,
									"name": "onTriggerBegin",
									"kind": 32768,
									"kindString": "Parameter",
									"flags": {
										"isOptional": true
									},
									"type": {
										"type": "reflection",
										"declaration": {
											"id": 28,
											"name": "__type",
											"kind": 65536,
											"kindString": "Type literal",
											"flags": {},
											"sources": [
												{
													"fileName": "PhysXPhysics.ts",
													"line": 117,
													"character": 21,
													"url": "https://github.com/galacean/engine/blob/bfd0960a/packages/physics-physx/src/PhysXPhysics.ts#L117"
												}
											],
											"signatures": [
												{
													"id": 29,
													"name": "__type",
													"kind": 4096,
													"kindString": "Call signature",
													"flags": {},
													"parameters": [
														{
															"id": 30,
															"name": "obj1",
															"kind": 32768,
															"kindString": "Parameter",
															"flags": {},
															"type": {
																"type": "intrinsic",
																"name": "number"
															}
														},
														{
															"id": 31,
															"name": "obj2",
															"kind": 32768,
															"kindString": "Parameter",
															"flags": {},
															"type": {
																"type": "intrinsic",
																"name": "number"
															}
														}
													],
													"type": {
														"type": "intrinsic",
														"name": "void"
													}
												}
											]
										}
									}
								},
								{
									"id": 32,
									"name": "onTriggerEnd",
									"kind": 32768,
									"kindString": "Parameter",
									"flags": {
										"isOptional": true
									},
									"type": {
										"type": "reflection",
										"declaration": {
											"id": 33,
											"name": "__type",
											"kind": 65536,
											"kindString": "Type literal",
											"flags": {},
											"sources": [
												{
													"fileName": "PhysXPhysics.ts",
													"line": 118,
													"character": 19,
													"url": "https://github.com/galacean/engine/blob/bfd0960a/packages/physics-physx/src/PhysXPhysics.ts#L118"
												}
											],
											"signatures": [
												{
													"id": 34,
													"name": "__type",
													"kind": 4096,
													"kindString": "Call signature",
													"flags": {},
													"parameters": [
														{
															"id": 35,
															"name": "obj1",
															"kind": 32768,
															"kindString": "Parameter",
															"flags": {},
															"type": {
																"type": "intrinsic",
																"name": "number"
															}
														},
														{
															"id": 36,
															"name": "obj2",
															"kind": 32768,
															"kindString": "Parameter",
															"flags": {},
															"type": {
																"type": "intrinsic",
																"name": "number"
															}
														}
													],
													"type": {
														"type": "intrinsic",
														"name": "void"
													}
												}
											]
										}
									}
								},
								{
									"id": 37,
									"name": "onTriggerStay",
									"kind": 32768,
									"kindString": "Parameter",
									"flags": {
										"isOptional": true
									},
									"type": {
										"type": "reflection",
										"declaration": {
											"id": 38,
											"name": "__type",
											"kind": 65536,
											"kindString": "Type literal",
											"flags": {},
											"sources": [
												{
													"fileName": "PhysXPhysics.ts",
													"line": 119,
													"character": 20,
													"url": "https://github.com/galacean/engine/blob/bfd0960a/packages/physics-physx/src/PhysXPhysics.ts#L119"
												}
											],
											"signatures": [
												{
													"id": 39,
													"name": "__type",
													"kind": 4096,
													"kindString": "Call signature",
													"flags": {},
													"parameters": [
														{
															"id": 40,
															"name": "obj1",
															"kind": 32768,
															"kindString": "Parameter",
															"flags": {},
															"type": {
																"type": "intrinsic",
																"name": "number"
															}
														},
														{
															"id": 41,
															"name": "obj2",
															"kind": 32768,
															"kindString": "Parameter",
															"flags": {},
															"type": {
																"type": "intrinsic",
																"name": "number"
															}
														}
													],
													"type": {
														"type": "intrinsic",
														"name": "void"
													}
												}
											]
										}
									}
								}
							],
							"type": {
								"type": "reference",
								"name": "IPhysicsManager"
							}
						}
					]
				},
				{
					"id": 52,
					"name": "createPhysicsMaterial",
					"kind": 2048,
					"kindString": "Method",
					"flags": {
						"isStatic": true
					},
					"sources": [
						{
							"fileName": "PhysXPhysics.ts",
							"line": 155,
							"character": 9,
							"url": "https://github.com/galacean/engine/blob/bfd0960a/packages/physics-physx/src/PhysXPhysics.ts#L155"
						}
					],
					"signatures": [
						{
							"id": 53,
							"name": "createPhysicsMaterial",
							"kind": 4096,
							"kindString": "Call signature",
							"flags": {},
							"comment": {
								"summary": [
									{
										"kind": "inline-tag",
										"tag": "@inheritDoc",
										"text": "IPhysics.createPhysicsMaterial"
									}
								]
							},
							"parameters": [
								{
									"id": 54,
									"name": "staticFriction",
									"kind": 32768,
									"kindString": "Parameter",
									"flags": {},
									"type": {
										"type": "intrinsic",
										"name": "number"
									}
								},
								{
									"id": 55,
									"name": "dynamicFriction",
									"kind": 32768,
									"kindString": "Parameter",
									"flags": {},
									"type": {
										"type": "intrinsic",
										"name": "number"
									}
								},
								{
									"id": 56,
									"name": "bounciness",
									"kind": 32768,
									"kindString": "Parameter",
									"flags": {},
									"type": {
										"type": "intrinsic",
										"name": "number"
									}
								},
								{
									"id": 57,
									"name": "frictionCombine",
									"kind": 32768,
									"kindString": "Parameter",
									"flags": {},
									"type": {
										"type": "intrinsic",
										"name": "number"
									}
								},
								{
									"id": 58,
									"name": "bounceCombine",
									"kind": 32768,
									"kindString": "Parameter",
									"flags": {},
									"type": {
										"type": "intrinsic",
										"name": "number"
									}
								}
							],
							"type": {
								"type": "reference",
								"name": "IPhysicsMaterial"
							}
						}
					]
				},
				{
					"id": 69,
					"name": "createPlaneColliderShape",
					"kind": 2048,
					"kindString": "Method",
					"flags": {
						"isStatic": true
					},
					"sources": [
						{
							"fileName": "PhysXPhysics.ts",
							"line": 186,
							"character": 9,
							"url": "https://github.com/galacean/engine/blob/bfd0960a/packages/physics-physx/src/PhysXPhysics.ts#L186"
						}
					],
					"signatures": [
						{
							"id": 70,
							"name": "createPlaneColliderShape",
							"kind": 4096,
							"kindString": "Call signature",
							"flags": {},
							"comment": {
								"summary": [
									{
										"kind": "inline-tag",
										"tag": "@inheritDoc",
										"text": "IPhysics.createPlaneColliderShape"
									}
								]
							},
							"parameters": [
								{
									"id": 71,
									"name": "uniqueID",
									"kind": 32768,
									"kindString": "Parameter",
									"flags": {},
									"type": {
										"type": "intrinsic",
										"name": "number"
									}
								},
								{
									"id": 72,
									"name": "material",
									"kind": 32768,
									"kindString": "Parameter",
									"flags": {},
									"type": {
										"type": "reference",
										"name": "PhysXPhysicsMaterial"
									}
								}
							],
							"type": {
								"type": "reference",
								"name": "IPlaneColliderShape"
							}
						}
					]
				},
				{
					"id": 64,
					"name": "createSphereColliderShape",
					"kind": 2048,
					"kindString": "Method",
					"flags": {
						"isStatic": true
					},
					"sources": [
						{
							"fileName": "PhysXPhysics.ts",
							"line": 175,
							"character": 9,
							"url": "https://github.com/galacean/engine/blob/bfd0960a/packages/physics-physx/src/PhysXPhysics.ts#L175"
						}
					],
					"signatures": [
						{
							"id": 65,
							"name": "createSphereColliderShape",
							"kind": 4096,
							"kindString": "Call signature",
							"flags": {},
							"comment": {
								"summary": [
									{
										"kind": "inline-tag",
										"tag": "@inheritDoc",
										"text": "IPhysics.createSphereColliderShape"
									}
								]
							},
							"parameters": [
								{
									"id": 66,
									"name": "uniqueID",
									"kind": 32768,
									"kindString": "Parameter",
									"flags": {},
									"type": {
										"type": "intrinsic",
										"name": "number"
									}
								},
								{
									"id": 67,
									"name": "radius",
									"kind": 32768,
									"kindString": "Parameter",
									"flags": {},
									"type": {
										"type": "intrinsic",
										"name": "number"
									}
								},
								{
									"id": 68,
									"name": "material",
									"kind": 32768,
									"kindString": "Parameter",
									"flags": {},
									"type": {
										"type": "reference",
										"name": "PhysXPhysicsMaterial"
									}
								}
							],
							"type": {
								"type": "reference",
								"name": "ISphereColliderShape"
							}
						}
					]
				},
				{
					"id": 85,
					"name": "createSpringJoint",
					"kind": 2048,
					"kindString": "Method",
					"flags": {
						"isStatic": true
					},
					"sources": [
						{
							"fileName": "PhysXPhysics.ts",
							"line": 219,
							"character": 9,
							"url": "https://github.com/galacean/engine/blob/bfd0960a/packages/physics-physx/src/PhysXPhysics.ts#L219"
						}
					],
					"signatures": [
						{
							"id": 86,
							"name": "createSpringJoint",
							"kind": 4096,
							"kindString": "Call signature",
							"flags": {},
							"comment": {
								"summary": [
									{
										"kind": "inline-tag",
										"tag": "@inheritDoc",
										"text": "IPhysics.createSpringJoint"
									}
								]
							},
							"parameters": [
								{
									"id": 87,
									"name": "collider",
									"kind": 32768,
									"kindString": "Parameter",
									"flags": {},
									"type": {
										"type": "reference",
										"name": "PhysXCollider"
									}
								}
							],
							"type": {
								"type": "reference",
								"name": "ISpringJoint"
							}
						}
					]
				},
				{
					"id": 42,
					"name": "createStaticCollider",
					"kind": 2048,
					"kindString": "Method",
					"flags": {
						"isStatic": true
					},
					"sources": [
						{
							"fileName": "PhysXPhysics.ts",
							"line": 134,
							"character": 9,
							"url": "https://github.com/galacean/engine/blob/bfd0960a/packages/physics-physx/src/PhysXPhysics.ts#L134"
						}
					],
					"signatures": [
						{
							"id": 43,
							"name": "createStaticCollider",
							"kind": 4096,
							"kindString": "Call signature",
							"flags": {},
							"comment": {
								"summary": [
									{
										"kind": "inline-tag",
										"tag": "@inheritDoc",
										"text": "IPhysics.createStaticCollider"
									}
								]
							},
							"parameters": [
								{
									"id": 44,
									"name": "position",
									"kind": 32768,
									"kindString": "Parameter",
									"flags": {},
									"type": {
										"type": "reference",
										"name": "Vector3"
									}
								},
								{
									"id": 45,
									"name": "rotation",
									"kind": 32768,
									"kindString": "Parameter",
									"flags": {},
									"type": {
										"type": "reference",
										"name": "Quaternion"
									}
								}
							],
							"type": {
								"type": "reference",
								"name": "IStaticCollider"
							}
						}
					]
				},
				{
					"id": 8,
					"name": "destroy",
					"kind": 2048,
					"kindString": "Method",
					"flags": {
						"isPublic": true,
						"isStatic": true
					},
					"sources": [
						{
							"fileName": "PhysXPhysics.ts",
							"line": 102,
							"character": 16,
							"url": "https://github.com/galacean/engine/blob/bfd0960a/packages/physics-physx/src/PhysXPhysics.ts#L102"
						}
					],
					"signatures": [
						{
							"id": 9,
							"name": "destroy",
							"kind": 4096,
							"kindString": "Call signature",
							"flags": {},
							"comment": {
								"summary": [
									{
										"kind": "text",
										"text": "Destroy PhysXPhysics."
									}
								]
							},
							"type": {
								"type": "intrinsic",
								"name": "void"
							}
						}
					]
				},
				{
					"id": 5,
					"name": "initialize",
					"kind": 2048,
					"kindString": "Method",
					"flags": {
						"isPublic": true,
						"isStatic": true
					},
					"sources": [
						{
							"fileName": "PhysXPhysics.ts",
							"line": 50,
							"character": 16,
							"url": "https://github.com/galacean/engine/blob/bfd0960a/packages/physics-physx/src/PhysXPhysics.ts#L50"
						}
					],
					"signatures": [
						{
							"id": 6,
							"name": "initialize",
							"kind": 4096,
							"kindString": "Call signature",
							"flags": {},
							"comment": {
								"summary": [
									{
										"kind": "text",
										"text": "Initialize PhysXPhysics."
									}
								],
								"blockTags": [
									{
										"tag": "@returns",
										"content": [
											{
												"kind": "text",
												"text": "Promise object"
											}
										]
									}
								]
							},
							"parameters": [
								{
									"id": 7,
									"name": "runtimeMode",
									"kind": 32768,
									"kindString": "Parameter",
									"flags": {},
									"comment": {
										"summary": [
											{
												"kind": "text",
												"text": "Runtime mode"
											}
										]
									},
									"type": {
										"type": "reference",
										"id": 93,
										"name": "PhysXRuntimeMode"
									},
									"defaultValue": "PhysXRuntimeMode.Auto"
								}
							],
							"type": {
								"type": "reference",
								"typeArguments": [
									{
										"type": "intrinsic",
										"name": "void"
									}
								],
								"name": "Promise",
								"qualifiedName": "Promise",
								"package": "typescript"
							}
						}
					]
				}
			],
			"groups": [
				{
					"title": "Constructors",
					"children": [
						91
					]
				},
				{
					"title": "Methods",
					"children": [
						88,
						59,
						73,
						50,
						46,
						79,
						82,
						10,
						52,
						69,
						64,
						85,
						42,
						8,
						5
					]
				}
			],
			"sources": [
				{
					"fileName": "PhysXPhysics.ts",
					"line": 37,
					"character": 13,
					"url": "https://github.com/galacean/engine/blob/bfd0960a/packages/physics-physx/src/PhysXPhysics.ts#L37"
				}
			]
		}
	],
	"groups": [
		{
			"title": "Enumerations",
			"children": [
				93
			]
		},
		{
			"title": "Classes",
			"children": [
				1
			]
		}
	],
	"sources": [
		{
			"fileName": "index.ts",
			"line": 1,
			"character": 0,
			"url": "https://github.com/galacean/engine/blob/bfd0960a/packages/physics-physx/src/index.ts#L1"
		}
	]
}